simple_aws_redshift/__init__.py
simple_aws_redshift/_version.py
simple_aws_redshift/api.py
simple_aws_redshift/connect.py
simple_aws_redshift/dialect.py
simple_aws_redshift/docs/__init__.py
simple_aws_redshift/lazy_imports.py
simple_aws_redshift/model.py
simple_aws_redshift/paths.py
simple_aws_redshift/redshift/__init__.py
simple_aws_redshift/redshift/api.py
simple_aws_redshift/redshift/client.py
simple_aws_redshift/redshift/model.py
simple_aws_redshift/redshift_data_api/__init__.py
simple_aws_redshift/redshift_data_api/api.py
simple_aws_redshift/redshift_data_api/client.py
simple_aws_redshift/redshift_data_api/model.py
simple_aws_redshift/redshift_serverless/__init__.py
simple_aws_redshift/redshift_serverless/api.py
simple_aws_redshift/redshift_serverless/client.py
simple_aws_redshift/redshift_serverless/model.py
simple_aws_redshift/tests/__init__.py
simple_aws_redshift/tests/bsm.py
simple_aws_redshift/tests/cdk_construct_def.py
simple_aws_redshift/tests/cdk_stack_def.py
simple_aws_redshift/tests/cdk_stack_init.py
simple_aws_redshift/tests/helper.py
simple_aws_redshift/tests/secrets.py
simple_aws_redshift/tests/settings.py
simple_aws_redshift/tests/test_property_helpers.py
simple_aws_redshift/utils.py
simple_aws_redshift/vendor/__init__.py
simple_aws_redshift/vendor/pytest_cov_helper.py
simple_aws_redshift/vendor/waiter.py
simple_aws_redshift-0.4.3.dist-info/AUTHORS.rst
simple_aws_redshift-0.4.3.dist-info/LICENSE.txt
simple_aws_redshift-0.4.3.dist-info/METADATA
simple_aws_redshift-0.4.3.dist-info/WHEEL
simple_aws_redshift-0.4.3.dist-info/RECORD
